[
    {
        "keyword": "Trust",
        "keyphrase": "Trust and denial",
        "summary": "A person may choose to ignore deception to maintain trust in a relationship."
    },
    {
        "keyword": "Deception",
        "keyphrase": "Awareness of deceit",
        "summary": "Someone can be aware of dishonesty but still decide to overlook it."
    },
    {
        "keyword": "Cognition",
        "keyphrase": "Selective perception",
        "summary": "People sometimes consciously choose not to acknowledge uncomfortable truths."
    },
    {
        "keyword": "Conflict",
        "keyphrase": "Internal conflict",
        "summary": "There can be an internal struggle between acknowledging reality and preserving peace."
    },
    {
        "keyword": "Avoidance",
        "keyphrase": "Avoidance of confrontation",
        "summary": "Individuals might avoid addressing lies to prevent conflict."
    }
]