[
    {
        "keyword": "Exclusivity",
        "keyphrase": "Unique involvement in wrongdoing",
        "summary": "Only one individual in a group has participated in illegal actions."
    },
    {
        "keyword": "Consequences",
        "keyphrase": "Facing repercussions for actions",
        "summary": "Engaging in criminal activity can lead to imprisonment."
    },
    {
        "keyword": "Judgment",
        "keyphrase": "Social differentiation based on behavior",
        "summary": "A person's actions can distinguish them from their peers."
    },
    {
        "keyword": "Accountability",
        "keyphrase": "Responsibility for one's actions",
        "summary": "Individuals must face the consequences of their unlawful behavior."
    }
]