[
    {
        "keyword": "Adaptability",
        "keyphrase": "Resourcefulness in constraints",
        "summary": "When faced with limitations, one can use available resources creatively to achieve success."
    },
    {
        "keyword": "Innovation",
        "keyphrase": "Embracing unconventional methods",
        "summary": "Unusual approaches can lead to recognition and success."
    },
    {
        "keyword": "Opportunity",
        "keyphrase": "Turning challenges into advantages",
        "summary": "Constraints can be transformed into opportunities for distinction and acclaim."
    }
]