[
    {
        "keyword": "Functionality",
        "keyphrase": "Limitations of broken tools",
        "summary": "A person cannot effectively use something that is damaged or incomplete."
    },
    {
        "keyword": "Utility",
        "keyphrase": "Necessity of intact resources",
        "summary": "To achieve a goal, the required resources or tools must be in proper condition."
    },
    {
        "keyword": "Preparation",
        "keyphrase": "Importance of readiness",
        "summary": "Success often depends on having functional and reliable means at one's disposal."
    },
    {
        "keyword": "Consequence",
        "keyphrase": "Impact of neglect",
        "summary": "Failing to maintain or repair essential items can hinder one's ability to accomplish tasks."
    }
]